MANIFEST.in
README.md
requirements.txt
setup.py
clients/__init__.py
clients/python/__init__.py
clients/python/client.py
clients/python/main.py
clients/python/terminal_symbols.py
eeguni.egg-info/PKG-INFO
eeguni.egg-info/SOURCES.txt
eeguni.egg-info/dependency_links.txt
eeguni.egg-info/top_level.txt
server/__init__.py
server/api.py
server/alphawaves/__init__.py
server/alphawaves/dataset.py
server/alphawaves/download.py
server/braininvaders2012/__init__.py
server/braininvaders2012/dataset.py
server/braininvaders2012/download.py
server/braininvaders2013/__init__.py
server/braininvaders2013/dataset.py
server/braininvaders2013/download.py
server/braininvaders2014a/__init__.py
server/braininvaders2014a/dataset.py
server/braininvaders2014a/download.py
server/braininvaders2014b/__init__.py
server/braininvaders2014b/dataset.py
server/braininvaders2014b/download.py
server/braininvaders2015a/__init__.py
server/braininvaders2015a/dataset.py
server/braininvaders2015a/download.py
server/braininvaders2015b/__init__.py
server/braininvaders2015b/dataset.py
server/braininvaders2015b/download.py
server/classif/__init__.py
server/classif/classification.py
server/classif/classification_wrapper.py
server/classif/cross_validation.py
server/classif/parameters.py
server/headmounted/__init__.py
server/headmounted/dataset.py
server/headmounted/download.py
server/lang/__init__.py
server/lang/request_interpreter.py
server/lang/terminal_symbols.py
server/moabb/__init__.py
server/moabb/run.py
server/moabb/utils.py
server/moabb/analysis/__init__.py
server/moabb/analysis/meta_analysis.py
server/moabb/analysis/plotting.py
server/moabb/analysis/results.py
server/moabb/datasets/Weibo2014.py
server/moabb/datasets/Zhou2016.py
server/moabb/datasets/__init__.py
server/moabb/datasets/alex_mi.py
server/moabb/datasets/base.py
server/moabb/datasets/bbci_eeg_fnirs.py
server/moabb/datasets/bnci.py
server/moabb/datasets/braininvaders.py
server/moabb/datasets/download.py
server/moabb/datasets/epfl.py
server/moabb/datasets/fake.py
server/moabb/datasets/gigadb.py
server/moabb/datasets/mpi_mi.py
server/moabb/datasets/physionet_mi.py
