Metadata-Version: 2.1
Name: eeguni
Version: 0.0.1
Summary: A server/client wrapper for EEG datasets
Home-page: https://github.com/gcattan/EEG_UNIFIED_ACCESS.git
Author: Gregoire Cattan
Author-email: gcattan@hotmail.fr
License: UNKNOWN
Platform: UNKNOWN
Classifier: Programming Language :: Python :: 3
Classifier: License :: OSI Approved :: GNU General Public License v3 (GPLv3)
Classifier: Operating System :: OS Independent
Classifier: Development Status :: 3 - Alpha
Classifier: Topic :: Scientific/Engineering
Requires-Python: >=3.6
